CHANGES.rst
CONTRIBUTORS.rst
MANIFEST.in
README.rst
buildout.cfg
heroku.cfg
setup.py
travis.cfg
src/rapido/__init__.py
src/rapido.plone.egg-info/PKG-INFO
src/rapido.plone.egg-info/SOURCES.txt
src/rapido.plone.egg-info/dependency_links.txt
src/rapido.plone.egg-info/entry_points.txt
src/rapido.plone.egg-info/namespace_packages.txt
src/rapido.plone.egg-info/not-zip-safe
src/rapido.plone.egg-info/requires.txt
src/rapido.plone.egg-info/top_level.txt
src/rapido/plone/__init__.py
src/rapido/plone/app.py
src/rapido/plone/configure.zcml
src/rapido/plone/handlers.py
src/rapido/plone/setuphandlers.py
src/rapido/plone/testing.py
src/rapido/plone/browser/__init__.py
src/rapido/plone/browser/call.py
src/rapido/plone/browser/configure.zcml
src/rapido/plone/browser/rapido.js
src/rapido/plone/browser/view.pt
src/rapido/plone/browser/views.py
src/rapido/plone/contentrule/__init__.py
src/rapido/plone/contentrule/action.py
src/rapido/plone/contentrule/configure.zcml
src/rapido/plone/locales/rapido.plone.pot
src/rapido/plone/locales/update.sh
src/rapido/plone/profiles/default/metadata.xml
src/rapido/plone/profiles/default/rapidoplone_marker.txt
src/rapido/plone/profiles/default/registry.xml
src/rapido/plone/profiles/mosaic/metadata.xml
src/rapido/plone/profiles/mosaic/registry.xml
src/rapido/plone/tests/__init__.py
src/rapido/plone/tests/configure.zcml
src/rapido/plone/tests/test_app.py
src/rapido/plone/tests/test_blocks.py
src/rapido/plone/tests/test_contentrule.py
src/rapido/plone/tests/test_handlers.py
src/rapido/plone/tests/test_http_commands.py
src/rapido/plone/tests/test_rest.py
src/rapido/plone/tests/test_robot.py
src/rapido/plone/tests/test_setup.py
src/rapido/plone/tests/other/rapido/app2/blocks/hello.html
src/rapido/plone/tests/resources/manifest.cfg
src/rapido/plone/tests/resources/rules.xml
src/rapido/plone/tests/resources/theme.html
src/rapido/plone/tests/resources/rapido/app2.lnk
src/rapido/plone/tests/resources/rapido/otherapp/blocks/purehtml.html
src/rapido/plone/tests/resources/rapido/testapp/settings.yaml
src/rapido/plone/tests/resources/rapido/testapp/blocks/action.html
src/rapido/plone/tests/resources/rapido/testapp/blocks/action.py
src/rapido/plone/tests/resources/rapido/testapp/blocks/action.yaml
src/rapido/plone/tests/resources/rapido/testapp/blocks/bad.pt
