Metadata-Version: 1.1
Name: rapido.plone
Version: 1.1.1
Summary: Rapido for Plone
Home-page: https://github.com/collective/rapido.plone
Author: Eric BREHAULT
Author-email: ebrehault@gmail.com
License: GPL
Keywords: Python Plone rapido
Platform: UNKNOWN
Classifier: Environment :: Web Environment
Classifier: Framework :: Plone
Classifier: Framework :: Plone :: 5.0
Classifier: Programming Language :: Python
Classifier: Programming Language :: Python :: 2.7
